adt/__init__.py
pyabstractdatatype-0.0.2.dist-info/LICENSE.txt
pyabstractdatatype-0.0.2.dist-info/METADATA
pyabstractdatatype-0.0.2.dist-info/WHEEL
pyabstractdatatype-0.0.2.dist-info/top_level.txt
pyabstractdatatype-0.0.2.dist-info/RECORD
