Metadata-Version: 2.1
Name: pyabstractdatatype
Version: 0.0.2
Summary: Abstract Data Types for Python
Author-email: Ángel Carvajal Ruiz <angelcaru10+pyadt@gmail.com>
Maintainer-email: Ángel Carvajal Ruiz <angelcaru10+pyadt@gmail.com>
Project-URL: Source Code, https://github.com/angelcaru/pyadt
Project-URL: Issues, https://github.com/angelcaru/pyadt/issues
Keywords: adt,data structure
Classifier: Development Status :: 3 - Alpha
Classifier: Intended Audience :: Developers
Classifier: Topic :: Software Development
Classifier: License :: OSI Approved :: MIT License
Classifier: Programming Language :: Python :: 3
Classifier: Programming Language :: Python :: 3.7
Classifier: Programming Language :: Python :: 3.8
Classifier: Programming Language :: Python :: 3.9
Classifier: Programming Language :: Python :: 3.10
Classifier: Programming Language :: Python :: 3.11
Classifier: Programming Language :: Python :: 3 :: Only
Requires-Python: >=3.7
License-File: LICENSE.txt
